sldp/__init__.py
sldp/chunkstats.py
sldp/config.py
sldp/preprocessannot.py
sldp/preprocesspheno.py
sldp/preprocessrefpanel.py
sldp/sldp.py
sldp/storyteller.py
sldp/weights.py
sldp-1.1.5.dist-info/METADATA
sldp-1.1.5.dist-info/WHEEL
sldp-1.1.5.dist-info/entry_points.txt
sldp-1.1.5.dist-info/top_level.txt
sldp-1.1.5.dist-info/RECORD
