Metadata-Version: 2.4
Name: sldp
Version: 1.1.5
Summary: Signed LD profile regression
Home-page: http://github.com/yakirr/sldp
Author: Yakir Reshef
Author-email: yreshef@broadinstitute.org
Project-URL: Bug Tracker, https://github.com/yakirr/sldp/issues
Project-URL: Tutorial, https://github.com/yakirr/sldp/blob/master/README.md
Classifier: Programming Language :: Python :: 3
Classifier: License :: OSI Approved :: MIT License
Classifier: Operating System :: OS Independent
Requires-Python: >=3
Requires-Dist: numpy
Requires-Dist: pandas>=2
Requires-Dist: scipy
Requires-Dist: matplotlib
Requires-Dist: gprim
Requires-Dist: ypy
